AsyncHttpsDNS/BlockedDomains.dat
AsyncHttpsDNS/__init__.py
AsyncHttpsDNS/server.py
AsyncHttpsDNS-0.0.9.dist-info/DESCRIPTION.rst
AsyncHttpsDNS-0.0.9.dist-info/METADATA
AsyncHttpsDNS-0.0.9.dist-info/RECORD
AsyncHttpsDNS-0.0.9.dist-info/WHEEL
AsyncHttpsDNS-0.0.9.dist-info/entry_points.txt
AsyncHttpsDNS-0.0.9.dist-info/metadata.json
AsyncHttpsDNS-0.0.9.dist-info/top_level.txt
