Metadata-Version: 2.0
Name: AsyncHttpsDNS
Version: 0.0.9
Summary: DNS Over Https Powered By Asyncio
Home-page: https://github.com/lifetyper/AsyncHttpsDNS
Author: Bi Qin
Author-email: leavic@gmail.com
License: MIT
Keywords: dns over https
Platform: UNKNOWN
Classifier: Development Status :: 3 - Alpha
Classifier: Intended Audience :: Developers
Classifier: Topic :: Software Development :: Build Tools
Classifier: License :: OSI Approved :: MIT License
Classifier: Programming Language :: Python :: 3.5
Classifier: Programming Language :: Python :: 3.6
Requires-Dist: aiodns (>=1.1.1)
Requires-Dist: aiohttp (>=2.0.7)
Requires-Dist: aiosocks (==0.2.2)
Requires-Dist: args (>=0.1.0)
Requires-Dist: cachetools (>=2.0.0)
Requires-Dist: dnslib (>=0.9.7)
Requires-Dist: dnspython (>=1.15.0)
Requires-Dist: retry (>=0.9.2)
